unir/__init__.py
unir/__main__.py
unir-0.1.0.dist-info/METADATA
unir-0.1.0.dist-info/WHEEL
unir-0.1.0.dist-info/entry_points.txt
unir-0.1.0.dist-info/licenses/LICENSE
unir-0.1.0.dist-info/RECORD
