Metadata-Version: 2.4
Name: unir
Version: 0.1.0
Summary: A unifier for IR datasets
License-File: LICENSE
Requires-Python: >=3.11
